{
  "train": [
    {
      "epoch": 1,
      "loss": 0.012864395536342636,
      "delta_mse": 0.012864395536342636,
      "delta_l1": 0.0
    },
    {
      "epoch": 2,
      "loss": 0.008048248525732197,
      "delta_mse": 0.008048248525732197,
      "delta_l1": 0.0
    },
    {
      "epoch": 3,
      "loss": 0.005467308581173711,
      "delta_mse": 0.005467308581173711,
      "delta_l1": 0.0
    },
    {
      "epoch": 4,
      "loss": 0.00464718781483316,
      "delta_mse": 0.00464718781483316,
      "delta_l1": 0.0
    },
    {
      "epoch": 5,
      "loss": 0.004300644619348895,
      "delta_mse": 0.004300644619348895,
      "delta_l1": 0.0
    },
    {
      "epoch": 6,
      "loss": 0.004142113850445094,
      "delta_mse": 0.004142113850445094,
      "delta_l1": 0.0
    },
    {
      "epoch": 7,
      "loss": 0.004033726231021138,
      "delta_mse": 0.004033726231021138,
      "delta_l1": 0.0
    },
    {
      "epoch": 8,
      "loss": 0.003982675947095049,
      "delta_mse": 0.003982675947095049,
      "delta_l1": 0.0
    },
    {
      "epoch": 9,
      "loss": 0.003943222556463661,
      "delta_mse": 0.003943222556463661,
      "delta_l1": 0.0
    },
    {
      "epoch": 10,
      "loss": 0.00393551717115497,
      "delta_mse": 0.00393551717115497,
      "delta_l1": 0.0
    }
  ],
  "val": [
    {
      "epoch": 1,
      "loss": 0.011499493499472737,
      "delta_mse": 0.011499493499472737,
      "delta_l1": 0.0,
      "delta_mae": 0.0685751115143299,
      "delta_norm_error": 0.2703312294721603
    },
    {
      "epoch": 2,
      "loss": 0.0063265194257604886,
      "delta_mse": 0.0063265194257604886,
      "delta_l1": 0.0,
      "delta_mae": 0.03395934297889471,
      "delta_norm_error": 0.1275909978121519
    },
    {
      "epoch": 3,
      "loss": 0.004544686504837591,
      "delta_mse": 0.004544686504837591,
      "delta_l1": 0.0,
      "delta_mae": 0.027802932973951103,
      "delta_norm_error": 0.10121995413154364
    },
    {
      "epoch": 4,
      "loss": 0.004075131418497767,
      "delta_mse": 0.004075131418497767,
      "delta_l1": 0.0,
      "delta_mae": 0.02651837741062045,
      "delta_norm_error": 0.09507852355241775
    },
    {
      "epoch": 5,
      "loss": 0.00406891413737103,
      "delta_mse": 0.00406891413737103,
      "delta_l1": 0.0,
      "delta_mae": 0.025736960271373392,
      "delta_norm_error": 0.09097005324587226
    },
    {
      "epoch": 6,
      "loss": 0.0037951384220948968,
      "delta_mse": 0.0037951384220948968,
      "delta_l1": 0.0,
      "delta_mae": 0.02392982932291925,
      "delta_norm_error": 0.0856949421145022
    },
    {
      "epoch": 7,
      "loss": 0.003993870189436711,
      "delta_mse": 0.003993870189436711,
      "delta_l1": 0.0,
      "delta_mae": 0.024231411388888954,
      "delta_norm_error": 0.08746672143265605
    },
    {
      "epoch": 8,
      "loss": 0.003914196911817999,
      "delta_mse": 0.003914196911817999,
      "delta_l1": 0.0,
      "delta_mae": 0.02593329940997064,
      "delta_norm_error": 0.09321115813553334
    },
    {
      "epoch": 9,
      "loss": 0.003798435269857873,
      "delta_mse": 0.003798435269857873,
      "delta_l1": 0.0,
      "delta_mae": 0.024293224620260297,
      "delta_norm_error": 0.08857451450303197
    },
    {
      "epoch": 10,
      "loss": 0.003765073613472123,
      "delta_mse": 0.003765073613472123,
      "delta_l1": 0.0,
      "delta_mae": 0.0250368752066046,
      "delta_norm_error": 0.09034511211067438
    }
  ]
}